README.md
setup.py
git_clone_dj.egg-info/PKG-INFO
git_clone_dj.egg-info/SOURCES.txt
git_clone_dj.egg-info/dependency_links.txt
git_clone_dj.egg-info/entry_points.txt
git_clone_dj.egg-info/requires.txt
git_clone_dj.egg-info/top_level.txt
gitt/main.py